issue_watcher/__init__.py
issue_watcher/constants.py
issue_watcher/github.py
issue_watcher/py.typed
issue_watcher/temporary_cache.py
issue_watcher-5.0.0.dist-info/WHEEL
issue_watcher-5.0.0.dist-info/METADATA
issue_watcher-5.0.0.dist-info/LICENSE
issue_watcher-5.0.0.dist-info/RECORD
