Metadata-Version: 2.1
Name: issue-watcher
Version: 5.0.0
Summary: Python test cases watching when an issue is closed and failing a test to let you know fixed functionality is available.
Home-page: https://github.com/radeklat/issue-watcher
License: MIT
Keywords: pytest,github,issues,testing
Author: Radek Lát
Author-email: radek.lat@gmail.com
Requires-Python: >=3.7.2,<=3.11
Classifier: Development Status :: 5 - Production/Stable
Classifier: Environment :: Console
Classifier: Intended Audience :: Developers
Classifier: License :: OSI Approved :: MIT License
Classifier: Operating System :: OS Independent
Classifier: Programming Language :: Python :: 3
Classifier: Programming Language :: Python :: 3.8
Classifier: Programming Language :: Python :: 3.9
Classifier: Programming Language :: Python :: 3.10
Classifier: Programming Language :: Python :: 3.11
Classifier: Programming Language :: Python :: 3.10
Classifier: Programming Language :: Python :: 3.11
Classifier: Programming Language :: Python :: 3.7
Classifier: Programming Language :: Python :: 3.8
Classifier: Programming Language :: Python :: 3.9
Classifier: Topic :: Software Development :: Bug Tracking
Classifier: Topic :: Software Development :: Libraries :: Python Modules
Classifier: Topic :: Software Development :: Quality Assurance
Classifier: Topic :: Software Development :: Testing :: Unit
Classifier: Topic :: System :: Monitoring
Classifier: Typing :: Typed
Requires-Dist: packaging
Requires-Dist: requests
Requires-Dist: semver
Requires-Dist: ujson
